SafeW/__init__.py
SafeW/safew.py
safew-2025.3.27.dist-info/WHEEL
safew-2025.3.27.dist-info/METADATA
safew-2025.3.27.dist-info/RECORD
