Metadata-Version: 2.4
Name: SafeW
Version: 2025.3.27
Summary: SafeW.org Bots Methods
Author-email: d9c <aymenmw@proton.me>
